authorization/__init__.py
authorization/__version__.py
authorization/authorization.py
authorization/descope_client.py
authorization/exceptions.py
lumberfi_authorization-0.1.0.dist-info/licenses/LICENSE
lumberfi_authorization-0.1.0.dist-info/METADATA
lumberfi_authorization-0.1.0.dist-info/WHEEL
lumberfi_authorization-0.1.0.dist-info/top_level.txt
lumberfi_authorization-0.1.0.dist-info/RECORD
