Metadata-Version: 2.4
Name: lumberfi-authorization
Version: 0.1.0
Summary: SDK for Descope token authorization and validation
Author: Lumberfi
Maintainer: Lumberfi
License: MIT
Project-URL: Homepage, https://github.com/lumberfi/lumberfi-authorization
Project-URL: Documentation, https://github.com/lumberfi/lumberfi-authorization#readme
Project-URL: Repository, https://github.com/lumberfi/lumberfi-authorization
Project-URL: Issues, https://github.com/lumberfi/lumberfi-authorization/issues
Keywords: descope,authorization,authentication,sdk,token,validation
Classifier: Development Status :: 4 - Beta
Classifier: Intended Audience :: Developers
Classifier: License :: OSI Approved :: MIT License
Classifier: Programming Language :: Python :: 3
Classifier: Programming Language :: Python :: 3.9
Classifier: Programming Language :: Python :: 3.10
Classifier: Programming Language :: Python :: 3.11
Classifier: Programming Language :: Python :: 3.12
Classifier: Topic :: Software Development :: Libraries :: Python Modules
Classifier: Topic :: Security
Requires-Python: >=3.9
License-File: LICENSE
Requires-Dist: descope==1.6.7
Provides-Extra: dev
Requires-Dist: pytest==8.3.2; extra == "dev"
Requires-Dist: pytest-cov==5.0.0; extra == "dev"
Requires-Dist: black==24.8.0; extra == "dev"
Requires-Dist: flake8==6.1.0; extra == "dev"
Requires-Dist: mypy>=1.0.0; extra == "dev"
Dynamic: license-file
